swagger_ui/__init__.py
swagger_ui/_version.py
swagger_ui/core.py
swagger_ui/utils.py
swagger_ui/handlers/__init__.py
swagger_ui/handlers/aiohttp.py
swagger_ui/handlers/bottle.py
swagger_ui/handlers/chalice.py
swagger_ui/handlers/falcon.py
swagger_ui/handlers/flask.py
swagger_ui/handlers/quart.py
swagger_ui/handlers/sanic.py
swagger_ui/handlers/starlette.py
swagger_ui/handlers/tornado.py
swagger_ui/static/LICENSE
swagger_ui/static/favicon-16x16.png
swagger_ui/static/favicon-32x32.png
swagger_ui/static/index.css
swagger_ui/static/oauth2-redirect.html
swagger_ui/static/swagger-editor-bundle.js
swagger_ui/static/swagger-editor-bundle.js.map
swagger_ui/static/swagger-editor-es-bundle-core.js
swagger_ui/static/swagger-editor-es-bundle-core.js.map
swagger_ui/static/swagger-editor-es-bundle.js
swagger_ui/static/swagger-editor-es-bundle.js.map
swagger_ui/static/swagger-editor-standalone-preset.js
swagger_ui/static/swagger-editor-standalone-preset.js.map
swagger_ui/static/swagger-editor.css
swagger_ui/static/swagger-editor.css.map
swagger_ui/static/swagger-editor.js
swagger_ui/static/swagger-editor.js.map
swagger_ui/static/swagger-initializer.js
swagger_ui/static/swagger-ui-bundle.js
swagger_ui/static/swagger-ui-es-bundle-core.js
swagger_ui/static/swagger-ui-es-bundle.js
swagger_ui/static/swagger-ui-standalone-preset.js
swagger_ui/static/swagger-ui.css
swagger_ui/static/swagger-ui.js
swagger_ui/templates/doc.html
swagger_ui/templates/editor.html
swagger_ui_python-1.0.4.dist-info/licenses/LICENSE
swagger_ui_python-1.0.4.dist-info/METADATA
swagger_ui_python-1.0.4.dist-info/WHEEL
swagger_ui_python-1.0.4.dist-info/top_level.txt
swagger_ui_python-1.0.4.dist-info/RECORD
