Metadata-Version: 2.4
Name: swagger-ui-python
Version: 1.0.4
Summary: Swagger UI for Python web framework, such as Tornado, Flask, Quart, Sanic and Falcon.
Author: SkyTik
License-Expression: Apache-2.0
Project-URL: Homepage, https://github.com/SkyTik/swagger-ui-python
Project-URL: Repository, https://github.com/SkyTik/swagger-ui-python
Project-URL: Issues, https://github.com/SkyTik/swagger-ui-python/issues
Keywords: swagger,swagger-ui,openapi,api,documentation,flask,tornado,sanic,quart,falcon,aiohttp,starlette,bottle,chalice
Classifier: Development Status :: 5 - Production/Stable
Classifier: Intended Audience :: Developers
Classifier: Operating System :: OS Independent
Classifier: Programming Language :: Python :: 3
Classifier: Programming Language :: Python :: 3.9
Classifier: Programming Language :: Python :: 3.10
Classifier: Programming Language :: Python :: 3.11
Classifier: Programming Language :: Python :: 3.12
Classifier: Programming Language :: Python :: 3.13
Classifier: Topic :: Software Development :: Documentation
Classifier: Topic :: Internet :: WWW/HTTP
Requires-Python: >=3.9
License-File: LICENSE
Requires-Dist: jinja2>=2.0
Requires-Dist: packaging>=20.0
Requires-Dist: PyYaml>=5.0
Dynamic: license-file
